{"note":"This file is an internal implementation detail to speed up HTML report generation. Its format can change at any time. You might be looking for the JSON report: https://coverage.rtfd.io/cmd.html#cmd-json","format":5,"version":"7.13.5","globals":"839b5bfdbd6eefee39f2b9922876a00a","files":{"z_7cc24e9b3f9e4fee_api_py":{"hash":"f8b40f39b39ae7297d9bba2f0e4cee26","index":{"url":"z_7cc24e9b3f9e4fee_api_py.html","file":"contracts_to_transactions/api.py","description":"","nums":{"precision":0,"n_files":1,"n_statements":22,"n_excluded":0,"n_missing":0,"n_branches":0,"n_partial_branches":0,"n_missing_branches":0}}},"z_7cc24e9b3f9e4fee_config_py":{"hash":"c7c83f70c08469844f462ea9b15bd4d5","index":{"url":"z_7cc24e9b3f9e4fee_config_py.html","file":"contracts_to_transactions/config.py","description":"","nums":{"precision":0,"n_files":1,"n_statements":21,"n_excluded":0,"n_missing":0,"n_branches":0,"n_partial_branches":0,"n_missing_branches":0}}},"z_7cc24e9b3f9e4fee_gx_validation_py":{"hash":"0015bfa85d4c5b18c39e232218572045","index":{"url":"z_7cc24e9b3f9e4fee_gx_validation_py.html","file":"contracts_to_transactions/gx_validation.py","description":"","nums":{"precision":0,"n_files":1,"n_statements":37,"n_excluded":0,"n_missing":37,"n_branches":0,"n_partial_branches":0,"n_missing_branches":0}}},"z_7cc24e9b3f9e4fee_io_utils_py":{"hash":"60fdd468119bf9090b69d295bd076d4d","index":{"url":"z_7cc24e9b3f9e4fee_io_utils_py.html","file":"contracts_to_transactions/io_utils.py","description":"","nums":{"precision":0,"n_files":1,"n_statements":24,"n_excluded":0,"n_missing":0,"n_branches":0,"n_partial_branches":0,"n_missing_branches":0}}},"z_7cc24e9b3f9e4fee_main_py":{"hash":"ea03c248489da31587d6f2d44e331901","index":{"url":"z_7cc24e9b3f9e4fee_main_py.html","file":"contracts_to_transactions/main.py","description":"","nums":{"precision":0,"n_files":1,"n_statements":50,"n_excluded":2,"n_missing":2,"n_branches":0,"n_partial_branches":0,"n_missing_branches":0}}},"z_7cc24e9b3f9e4fee_schemas_py":{"hash":"11d2db51a401d9ffb1695547b74128ca","index":{"url":"z_7cc24e9b3f9e4fee_schemas_py.html","file":"contracts_to_transactions/schemas.py","description":"","nums":{"precision":0,"n_files":1,"n_statements":2,"n_excluded":0,"n_missing":0,"n_branches":0,"n_partial_branches":0,"n_missing_branches":0}}},"z_7cc24e9b3f9e4fee_transform_py":{"hash":"e65ea77b1bd7117071ea86b959e1ff8c","index":{"url":"z_7cc24e9b3f9e4fee_transform_py.html","file":"contracts_to_transactions/transform.py","description":"","nums":{"precision":0,"n_files":1,"n_statements":86,"n_excluded":0,"n_missing":0,"n_branches":0,"n_partial_branches":0,"n_missing_branches":0}}},"z_7cc24e9b3f9e4fee_validate_py":{"hash":"500ff4116e4d9ffac859108ca6db4518","index":{"url":"z_7cc24e9b3f9e4fee_validate_py.html","file":"contracts_to_transactions/validate.py","description":"","nums":{"precision":0,"n_files":1,"n_statements":26,"n_excluded":0,"n_missing":8,"n_branches":0,"n_partial_branches":0,"n_missing_branches":0}}}}}